rregex-0.1.1.dist-info/METADATA
rregex-0.1.1.dist-info/WHEEL
rregex.libs/libgcc_s-1e52349c.so.1
rregex/__init__.py
rregex/rregex.cpython-310-x86_64-linux-gnu.so
rregex-0.1.1.dist-info/RECORD
